dtb/__init__.py
dtb-0.0.2.dist-info/LICENSE
dtb-0.0.2.dist-info/METADATA
dtb-0.0.2.dist-info/WHEEL
dtb-0.0.2.dist-info/top_level.txt
dtb-0.0.2.dist-info/RECORD
